[
  {
    "title": "Don't Sweat It",
    "id": "dont-sweat-it",
    "links": [
      {
        "title": "SoundCloud",
        "url": "https://soundcloud.com/stefanbohacek/dont-sweat-it?in=stefanbohacek/sets/mixtape"        
      },
      {
        "title": "Bandcamp",
        "url": "https://stefanbohacek.bandcamp.com/track/dont-sweat-it"        
      },
      {
        "title": "Bandwagon",
        "url": "https://bandwagon.fm/66b15d8c137a3fc2e6d862cb"        
      },
      {
        "title": "Mirlo",
        "url": "https://mirlo.space/stefan/release/dont-sweat-it"        
      }
    ]
  },
  {
    "title": "Secret Places",
    "id": "secret-places",
    "links": [
      {
        "title": "SoundCloud",
        "url": "https://soundcloud.com/stefanbohacek/secret-places?in=stefanbohacek/sets/mixtape"        
      },
      {
        "title": "Bandcamp",
        "url": "https://stefanbohacek.bandcamp.com/track/secret-places"        
      },
      {
        "title": "Bandwagon",
        "url": "https://bandwagon.fm/66e38b044c86ea48ed036c27"        
      },
      {
        "title": "Mirlo",
        "url": "https://mirlo.space/stefan/release/secret-places"        
      }
    ]
  },
  {
    "title": "Flames",
    "id": "flames",
    "links": [
      {
        "title": "SoundCloud",
        "url": "https://soundcloud.com/stefanbohacek/flames?in=stefanbohacek/sets/mixtape"        
      }
    ]
  },
  {
    "title": "Nothing But Me",
    "id": "nothing-but-me",
    "links": [
      {
        "title": "SoundCloud",
        "url": "https://soundcloud.com/stefanbohacek/nothing-but-me?in=stefanbohacek/sets/mixtape"        
      }
    ]
  },
  {
    "title": "I Love Pressure",
    "id": "i-love-pressure",
    "links": [
      {
        "title": "SoundCloud",
        "url": "https://soundcloud.com/stefanbohacek/i-love-pressure?in=stefanbohacek/sets/piano"        
      }
    ]
  },
  {
    "title": "Narrow Escape",
    "id": "narrow-escape",
    "links": [
      {
        "title": "SoundCloud",
        "url": "https://soundcloud.com/stefanbohacek/narrow-escape?in=stefanbohacek/sets/orchestral-cinematic-instrumental"        
      }
    ]
  },
  {
    "title": "More Than Twice",
    "id": "more-than-twice",
    "links": [
      {
        "title": "SoundCloud",
        "url": "https://soundcloud.com/stefanbohacek/more-than-twice?in=stefanbohacek/sets/orchestral-cinematic-instrumental"        
      }
    ]
  },
  {
    "title": "Scared to Death but Saddling up Anyway",
    "id": "scared-to-death-but-saddling-up-anyway",
    "links": [
      {
        "title": "SoundCloud",
        "url": "https://soundcloud.com/stefanbohacek/scared-to-death-but-saddling-up-anyway?in=stefanbohacek/sets/orchestral-cinematic-instrumental"        
      }
    ]
  }
]